thinkingkey/__init__.py
thinkingkey/__main__.py
thinkingkey/core/greet.py
thinkingkey/info/project_info.py
thinkingkey-0.0.1.dist-info/licenses/LICENSE
thinkingkey-0.0.1.dist-info/METADATA
thinkingkey-0.0.1.dist-info/WHEEL
thinkingkey-0.0.1.dist-info/RECORD
